speedruncompy/__init__.py
speedruncompy/api.py
speedruncompy/auth.py
speedruncompy/config.py
speedruncompy/endpoints.py
speedruncompy/exceptions.py
speedruncompy/py.typed
speedruncompy/datatypes/__init__.py
speedruncompy/datatypes/_impl.py
speedruncompy/datatypes/defs.py
speedruncompy/datatypes/enums.py
speedruncompy/datatypes/responses.py
speedruncompy/scripts/__init__.py
speedruncompy/scripts/srcompy_login.py
speedruncompy-1.0.1.dist-info/METADATA
speedruncompy-1.0.1.dist-info/WHEEL
speedruncompy-1.0.1.dist-info/entry_points.txt
speedruncompy-1.0.1.dist-info/licenses/LICENSE
speedruncompy-1.0.1.dist-info/RECORD
