Metadata-Version: 2.4
Name: speedruncompy
Version: 1.0.1
Summary: A wrapper for speedrun.com's obscure new v2 API, as used by their new site
Project-URL: Homepage, https://github.com/ManicJamie/speedruncompy
Project-URL: Repository, https://github.com/ManicJamie/speedruncompy.git
Project-URL: Bug Tracker, https://github.com/ManicJamie/speedruncompy/issues
Author-email: Jamie <jamie.on.twitch@gmail.com>
License: LGPLv2.1
License-File: LICENSE
Keywords: speedrun
Classifier: Development Status :: 4 - Beta
Classifier: License :: OSI Approved :: GNU Lesser General Public License v2 (LGPLv2)
Classifier: Operating System :: OS Independent
Classifier: Programming Language :: Python :: 3
Requires-Python: >=3.11
Requires-Dist: aiohttp[speedups]~=3.13.2
Requires-Dist: bidict~=0.23.1
Requires-Dist: pydantic~=2.12.5
Provides-Extra: test
Requires-Dist: pytest; extra == 'test'
Requires-Dist: pytest-asyncio; extra == 'test'
Requires-Dist: pytest-cov; extra == 'test'
Requires-Dist: python-dotenv; extra == 'test'
